tailx-0.1.5.dist-info/METADATA
tailx-0.1.5.dist-info/WHEEL
tailx-0.1.5.dist-info/entry_points.txt
tailx/__init__.py
tailx-0.1.5.dist-info/RECORD
