Metadata-Version: 2.1
Name: tailx
Version: 0.1.5
Summary: tailx, 带颜色的 `tail -f`, 更好看的查看日志
Home-page: https://github.com/jiaosenvip/tailx
Author: jiaosenvip
Author-Email: jiaosenvip <jiaosenvip@163.com>
License: MIT
Project-URL: Homepage, https://github.com/jiaosenvip/tailx
Requires-Python: >=3.9
Requires-Dist: rich
